autohooks/plugins/pytest/__init__.py
autohooks/plugins/pytest/__version__.py
autohooks/plugins/pytest/pytest.py
autohooks_plugin_pytest-23.10.0.dist-info/LICENSE
autohooks_plugin_pytest-23.10.0.dist-info/METADATA
autohooks_plugin_pytest-23.10.0.dist-info/WHEEL
autohooks_plugin_pytest-23.10.0.dist-info/RECORD
