Metadata-Version: 2.1
Name: autohooks-plugin-pytest
Version: 23.10.0
Summary: An autohooks plugin for pytest
Home-page: https://github.com/greenbone/autohooks-plugin-pytest
License: GPL-3.0-or-later
Keywords: git,formatting,linting,hooks,pytest
Author: Greenbone AG
Author-email: info@greenbone.net
Requires-Python: >=3.9,<4.0
Classifier: Development Status :: 5 - Production/Stable
Classifier: Environment :: Console
Classifier: Intended Audience :: Developers
Classifier: License :: OSI Approved :: GNU General Public License v3 or later (GPLv3+)
Classifier: Operating System :: OS Independent
Classifier: Programming Language :: Python :: 3
Classifier: Programming Language :: Python :: 3.9
Classifier: Programming Language :: Python :: 3.10
Classifier: Programming Language :: Python :: 3.11
Classifier: Programming Language :: Python :: 3.12
Classifier: Topic :: Software Development :: Libraries :: Python Modules
Requires-Dist: autohooks (>=21.3)
Requires-Dist: pytest (>=7.1.2)
Project-URL: Repository, https://github.com/greenbone/autohooks-plugin-pytest
